oat_python-0.2.0.dist-info/METADATA
oat_python-0.2.0.dist-info/WHEEL
oat_python-0.2.0.dist-info/licenses/LICENSE
oat_python.libs/libgcc_s-27e5a392.so.1
oat_python/README.md
oat_python/__init__.py
oat_python/_test.py
oat_python/barcode.py
oat_python/core.pypy310-pp73-x86-linux-gnu.so
oat_python/data/__init__.py
oat_python/data/stanford_dragon.txt
oat_python/dissimilarity.py
oat_python/homology.py
oat_python/hypergraph.py
oat_python/matrix.py
oat_python/plot.py
oat_python/point_cloud.py
oat_python/simplex.py
oat_python-0.2.0.dist-info/RECORD
