Metadata-Version: 2.4
Name: oat_python
Version: 0.2.0
Requires-Dist: hypernetx
Requires-Dist: ipython
Requires-Dist: matplotlib
Requires-Dist: maturin
Requires-Dist: nbformat
Requires-Dist: networkx
Requires-Dist: numpy
Requires-Dist: pandas
Requires-Dist: plotly
Requires-Dist: scikit-learn
Requires-Dist: scipy
Requires-Dist: tqdm
Requires-Dist: sphinx
Requires-Dist: sphinx-rtd-theme
Requires-Dist: sphinx-gallery
Requires-Dist: sphinx-autodoc-typehints
License-File: LICENSE
Home-Page: https://openappliedtopology.github.io
Project-URL: Documentation, https://oat-python.readthedocs.io
